mcu_functions/__init__.py
mcu_functions/flatbuffers_to_json_with_flatc.py
mcu_functions/functions.py
mcu_functions/utils.py
mcu_protocol/__init__.py
mcu_protocol/com_address.py
mcu_protocol/content_payload.py
mcu_protocol/driver_type.py
mcu_protocol/ejector_data.py
mcu_protocol/empty_payload.py
mcu_protocol/function_id.py
mcu_protocol/io_address_batch.py
mcu_protocol/io_address_long.py
mcu_protocol/io_operation.py
mcu_protocol/io_operation_batch.py
mcu_protocol/io_status.py
mcu_protocol/io_status_batch.py
mcu_protocol/meta_info.py
mcu_protocol/motor_basic_info.py
mcu_protocol/motor_control_operation.py
mcu_protocol/motor_direction.py
mcu_protocol/motor_operation.py
mcu_protocol/motor_speed.py
mcu_protocol/motor_stats.py
mcu_protocol/read_trigger_count.py
mcu_protocol/request.py
mcu_protocol/response.py
mcu_protocol/sensor_data.py
mcu_protocol/sensor_query_interval.py
mcu_protocol/serial_number.py
mcu_protocol/trigger_start_position.py
mcu_protocol/unix_time_stamp.py
mcu_communication_protocol-1.0.2.dist-info/METADATA
mcu_communication_protocol-1.0.2.dist-info/WHEEL
mcu_communication_protocol-1.0.2.dist-info/top_level.txt
mcu_communication_protocol-1.0.2.dist-info/RECORD
